{"nodes": [{"id": "backtesting_reporting_reader_py", "label": "reader.py", "file_type": "code", "source_file": "backtesting/reporting/reader.py", "source_location": "L1"}, {"id": "reader_runreader", "label": "RunReader", "file_type": "code", "source_file": "backtesting/reporting/reader.py", "source_location": "L9"}, {"id": "reader_runreader_read", "label": ".read()", "file_type": "code", "source_file": "backtesting/reporting/reader.py", "source_location": "L10"}, {"id": "reader_read_series", "label": "_read_series()", "file_type": "code", "source_file": "backtesting/reporting/reader.py", "source_location": "L34"}, {"id": "reader_read_optional_series", "label": "_read_optional_series()", "file_type": "code", "source_file": "backtesting/reporting/reader.py", "source_location": "L39"}, {"id": "reader_read_optional_frame", "label": "_read_optional_frame()", "file_type": "code", "source_file": "backtesting/reporting/reader.py", "source_location": "L46"}, {"id": "reader_read_optional_parquet", "label": "_read_optional_parquet()", "file_type": "code", "source_file": "backtesting/reporting/reader.py", "source_location": "L52"}, {"id": "reader_read_optional_json", "label": "_read_optional_json()", "file_type": "code", "source_file": "backtesting/reporting/reader.py", "source_location": "L58"}], "edges": [{"source": "backtesting_reporting_reader_py", "target": "json", "relation": "imports", "confidence": "EXTRACTED", "source_file": "backtesting/reporting/reader.py", "source_location": "L1", "weight": 1.0}, {"source": "backtesting_reporting_reader_py", "target": "pathlib", "relation": "imports_from", "confidence": "EXTRACTED", "source_file": "backtesting/reporting/reader.py", "source_location": "L2", "weight": 1.0}, {"source": "backtesting_reporting_reader_py", "target": "pandas", "relation": "imports", "confidence": "EXTRACTED", "source_file": "backtesting/reporting/reader.py", "source_location": "L4", "weight": 1.0}, {"source": "backtesting_reporting_reader_py", "target": "backtesting_reporting_models_py", "relation": "imports_from", "confidence": "EXTRACTED", "source_file": "backtesting/reporting/reader.py", "source_location": "L6", "weight": 1.0}, {"source": "backtesting_reporting_reader_py", "target": "reader_runreader", "relation": "contains", "confidence": "EXTRACTED", "source_file": "backtesting/reporting/reader.py", "source_location": "L9", "weight": 1.0}, {"source": "reader_runreader", "target": "reader_runreader_read", "relation": "method", "confidence": "EXTRACTED", "source_file": "backtesting/reporting/reader.py", "source_location": "L10", "weight": 1.0}, {"source": "backtesting_reporting_reader_py", "target": "reader_read_series", "relation": "contains", "confidence": "EXTRACTED", "source_file": "backtesting/reporting/reader.py", "source_location": "L34", "weight": 1.0}, {"source": "backtesting_reporting_reader_py", "target": "reader_read_optional_series", "relation": "contains", "confidence": "EXTRACTED", "source_file": "backtesting/reporting/reader.py", "source_location": "L39", "weight": 1.0}, {"source": "backtesting_reporting_reader_py", "target": "reader_read_optional_frame", "relation": "contains", "confidence": "EXTRACTED", "source_file": "backtesting/reporting/reader.py", "source_location": "L46", "weight": 1.0}, {"source": "backtesting_reporting_reader_py", "target": "reader_read_optional_parquet", "relation": "contains", "confidence": "EXTRACTED", "source_file": "backtesting/reporting/reader.py", "source_location": "L52", "weight": 1.0}, {"source": "backtesting_reporting_reader_py", "target": "reader_read_optional_json", "relation": "contains", "confidence": "EXTRACTED", "source_file": "backtesting/reporting/reader.py", "source_location": "L58", "weight": 1.0}, {"source": "reader_runreader_read", "target": "reader_read_series", "relation": "calls", "confidence": "EXTRACTED", "source_file": "backtesting/reporting/reader.py", "source_location": "L19", "weight": 1.0}, {"source": "reader_runreader_read", "target": "reader_read_optional_series", "relation": "calls", "confidence": "EXTRACTED", "source_file": "backtesting/reporting/reader.py", "source_location": "L24", "weight": 1.0}, {"source": "reader_runreader_read", "target": "reader_read_optional_frame", "relation": "calls", "confidence": "EXTRACTED", "source_file": "backtesting/reporting/reader.py", "source_location": "L25", "weight": 1.0}, {"source": "reader_runreader_read", "target": "reader_read_optional_parquet", "relation": "calls", "confidence": "EXTRACTED", "source_file": "backtesting/reporting/reader.py", "source_location": "L27", "weight": 1.0}, {"source": "reader_runreader_read", "target": "reader_read_optional_json", "relation": "calls", "confidence": "EXTRACTED", "source_file": "backtesting/reporting/reader.py", "source_location": "L28", "weight": 1.0}], "raw_calls": [{"caller_nid": "reader_runreader_read", "callee": "Path", "source_file": "backtesting/reporting/reader.py", "source_location": "L11"}, {"caller_nid": "reader_runreader_read", "callee": "SavedRun", "source_file": "backtesting/reporting/reader.py", "source_location": "L14"}, {"caller_nid": "reader_runreader_read", "callee": "loads", "source_file": "backtesting/reporting/reader.py", "source_location": "L17"}, {"caller_nid": "reader_runreader_read", "callee": "read_text", "source_file": "backtesting/reporting/reader.py", "source_location": "L17"}, {"caller_nid": "reader_runreader_read", "callee": "loads", "source_file": "backtesting/reporting/reader.py", "source_location": "L18"}, {"caller_nid": "reader_runreader_read", "callee": "read_text", "source_file": "backtesting/reporting/reader.py", "source_location": "L18"}, {"caller_nid": "reader_runreader_read", "callee": "read_parquet", "source_file": "backtesting/reporting/reader.py", "source_location": "L22"}, {"caller_nid": "reader_runreader_read", "callee": "read_parquet", "source_file": "backtesting/reporting/reader.py", "source_location": "L23"}, {"caller_nid": "reader_read_series", "callee": "read_csv", "source_file": "backtesting/reporting/reader.py", "source_location": "L35"}, {"caller_nid": "reader_read_series", "callee": "set_index", "source_file": "backtesting/reporting/reader.py", "source_location": "L36"}, {"caller_nid": "reader_read_optional_series", "callee": "exists", "source_file": "backtesting/reporting/reader.py", "source_location": "L40"}, {"caller_nid": "reader_read_optional_series", "callee": "read_csv", "source_file": "backtesting/reporting/reader.py", "source_location": "L42"}, {"caller_nid": "reader_read_optional_series", "callee": "set_index", "source_file": "backtesting/reporting/reader.py", "source_location": "L43"}, {"caller_nid": "reader_read_optional_frame", "callee": "exists", "source_file": "backtesting/reporting/reader.py", "source_location": "L47"}, {"caller_nid": "reader_read_optional_frame", "callee": "read_csv", "source_file": "backtesting/reporting/reader.py", "source_location": "L49"}, {"caller_nid": "reader_read_optional_parquet", "callee": "exists", "source_file": "backtesting/reporting/reader.py", "source_location": "L53"}, {"caller_nid": "reader_read_optional_parquet", "callee": "read_parquet", "source_file": "backtesting/reporting/reader.py", "source_location": "L55"}, {"caller_nid": "reader_read_optional_json", "callee": "loads", "source_file": "backtesting/reporting/reader.py", "source_location": "L59"}, {"caller_nid": "reader_read_optional_json", "callee": "read_text", "source_file": "backtesting/reporting/reader.py", "source_location": "L59"}, {"caller_nid": "reader_read_optional_json", "callee": "exists", "source_file": "backtesting/reporting/reader.py", "source_location": "L59"}]}