{"nodes": [{"id": "backtesting_reporting_snapshots_py", "label": "snapshots.py", "file_type": "code", "source_file": "backtesting/reporting/snapshots.py", "source_location": "L1"}, {"id": "snapshots_default_benchmark", "label": "_default_benchmark()", "file_type": "code", "source_file": "backtesting/reporting/snapshots.py", "source_location": "L43"}, {"id": "snapshots_empty_series", "label": "_empty_series()", "file_type": "code", "source_file": "backtesting/reporting/snapshots.py", "source_location": "L47"}, {"id": "snapshots_performancesnapshot", "label": "PerformanceSnapshot", "file_type": "code", "source_file": "backtesting/reporting/snapshots.py", "source_location": "L52"}, {"id": "snapshots_performancesnapshotfactory", "label": "PerformanceSnapshotFactory", "file_type": "code", "source_file": "backtesting/reporting/snapshots.py", "source_location": "L71"}, {"id": "snapshots_performancesnapshotfactory_init", "label": ".__init__()", "file_type": "code", "source_file": "backtesting/reporting/snapshots.py", "source_location": "L72"}, {"id": "snapshots_performancesnapshotfactory_build", "label": ".build()", "file_type": "code", "source_file": "backtesting/reporting/snapshots.py", "source_location": "L76"}, {"id": "snapshots_performancesnapshotfactory_load_benchmark", "label": "._load_benchmark()", "file_type": "code", "source_file": "backtesting/reporting/snapshots.py", "source_location": "L124"}, {"id": "snapshots_performancesnapshotfactory_resolve_profile", "label": "._resolve_profile()", "file_type": "code", "source_file": "backtesting/reporting/snapshots.py", "source_location": "L149"}, {"id": "snapshots_performancesnapshotfactory_build_metrics", "label": "._build_metrics()", "file_type": "code", "source_file": "backtesting/reporting/snapshots.py", "source_location": "L171"}, {"id": "snapshots_performancesnapshotfactory_build_rolling_metrics", "label": "._build_rolling_metrics()", "file_type": "code", "source_file": "backtesting/reporting/snapshots.py", "source_location": "L261"}, {"id": "snapshots_performancesnapshotfactory_build_drawdowns", "label": "._build_drawdowns()", "file_type": "code", "source_file": "backtesting/reporting/snapshots.py", "source_location": "L306"}, {"id": "snapshots_performancesnapshotfactory_build_exposure", "label": "._build_exposure()", "file_type": "code", "source_file": "backtesting/reporting/snapshots.py", "source_location": "L358"}, {"id": "snapshots_performancesnapshotfactory_build_sectors", "label": "._build_sectors()", "file_type": "code", "source_file": "backtesting/reporting/snapshots.py", "source_location": "L373"}, {"id": "snapshots_performancesnapshotfactory_build_research", "label": "._build_research()", "file_type": "code", "source_file": "backtesting/reporting/snapshots.py", "source_location": "L380"}, {"id": "snapshots_performancesnapshotfactory_latest_holdings_relative_performance", "label": "._latest_holdings_relative_performance()", "file_type": "code", "source_file": "backtesting/reporting/snapshots.py", "source_location": "L407"}, {"id": "snapshots_performancesnapshotfactory_compute_latest_holdings_returns", "label": "._compute_latest_holdings_returns()", "file_type": "code", "source_file": "backtesting/reporting/snapshots.py", "source_location": "L422"}, {"id": "snapshots_merge_latest_holdings_returns", "label": "_merge_latest_holdings_returns()", "file_type": "code", "source_file": "backtesting/reporting/snapshots.py", "source_location": "L452"}, {"id": "snapshots_rank_latest_holdings", "label": "_rank_latest_holdings()", "file_type": "code", "source_file": "backtesting/reporting/snapshots.py", "source_location": "L475"}, {"id": "snapshots_performancesnapshotfactory_decorate_holding_symbols", "label": "._decorate_holding_symbols()", "file_type": "code", "source_file": "backtesting/reporting/snapshots.py", "source_location": "L484"}, {"id": "snapshots_latest_rebalance_date", "label": "_latest_rebalance_date()", "file_type": "code", "source_file": "backtesting/reporting/snapshots.py", "source_location": "L492"}, {"id": "snapshots_latest_holdings", "label": "_latest_holdings()", "file_type": "code", "source_file": "backtesting/reporting/snapshots.py", "source_location": "L510"}, {"id": "snapshots_equity_from_returns", "label": "_equity_from_returns()", "file_type": "code", "source_file": "backtesting/reporting/snapshots.py", "source_location": "L523"}, {"id": "snapshots_cagr", "label": "_cagr()", "file_type": "code", "source_file": "backtesting/reporting/snapshots.py", "source_location": "L527"}, {"id": "snapshots_build_drawdown_record", "label": "_build_drawdown_record()", "file_type": "code", "source_file": "backtesting/reporting/snapshots.py", "source_location": "L542"}], "edges": [{"source": "backtesting_reporting_snapshots_py", "target": "dataclasses", "relation": "imports_from", "confidence": "EXTRACTED", "source_file": "backtesting/reporting/snapshots.py", "source_location": "L3", "weight": 1.0}, {"source": "backtesting_reporting_snapshots_py", "target": "numpy", "relation": "imports", "confidence": "EXTRACTED", "source_file": "backtesting/reporting/snapshots.py", "source_location": "L5", "weight": 1.0}, {"source": "backtesting_reporting_snapshots_py", "target": "pandas", "relation": "imports", "confidence": "EXTRACTED", "source_file": "backtesting/reporting/snapshots.py", "source_location": "L6", "weight": 1.0}, {"source": "backtesting_reporting_snapshots_py", "target": "backtesting_reporting_analytics_py", "relation": "imports_from", "confidence": "EXTRACTED", "source_file": "backtesting/reporting/snapshots.py", "source_location": "L8", "weight": 1.0}, {"source": "backtesting_reporting_snapshots_py", "target": "backtesting_reporting_benchmarks_py", "relation": "imports_from", "confidence": "EXTRACTED", "source_file": "backtesting/reporting/snapshots.py", "source_location": "L39", "weight": 1.0}, {"source": "backtesting_reporting_snapshots_py", "target": "backtesting_reporting_models_py", "relation": "imports_from", "confidence": "EXTRACTED", "source_file": "backtesting/reporting/snapshots.py", "source_location": "L40", "weight": 1.0}, {"source": "backtesting_reporting_snapshots_py", "target": "snapshots_default_benchmark", "relation": "contains", "confidence": "EXTRACTED", "source_file": "backtesting/reporting/snapshots.py", "source_location": "L43", "weight": 1.0}, {"source": "backtesting_reporting_snapshots_py", "target": "snapshots_empty_series", "relation": "contains", "confidence": "EXTRACTED", "source_file": "backtesting/reporting/snapshots.py", "source_location": "L47", "weight": 1.0}, {"source": "backtesting_reporting_snapshots_py", "target": "snapshots_performancesnapshot", "relation": "contains", "confidence": "EXTRACTED", "source_file": "backtesting/reporting/snapshots.py", "source_location": "L52", "weight": 1.0}, {"source": "backtesting_reporting_snapshots_py", "target": "snapshots_performancesnapshotfactory", "relation": "contains", "confidence": "EXTRACTED", "source_file": "backtesting/reporting/snapshots.py", "source_location": "L71", "weight": 1.0}, {"source": "snapshots_performancesnapshotfactory", "target": "snapshots_performancesnapshotfactory_init", "relation": "method", "confidence": "EXTRACTED", "source_file": "backtesting/reporting/snapshots.py", "source_location": "L72", "weight": 1.0}, {"source": "snapshots_performancesnapshotfactory", "target": "snapshots_performancesnapshotfactory_build", "relation": "method", "confidence": "EXTRACTED", "source_file": "backtesting/reporting/snapshots.py", "source_location": "L76", "weight": 1.0}, {"source": "snapshots_performancesnapshotfactory", "target": "snapshots_performancesnapshotfactory_load_benchmark", "relation": "method", "confidence": "EXTRACTED", "source_file": "backtesting/reporting/snapshots.py", "source_location": "L124", "weight": 1.0}, {"source": "snapshots_performancesnapshotfactory", "target": "snapshots_performancesnapshotfactory_resolve_profile", "relation": "method", "confidence": "EXTRACTED", "source_file": "backtesting/reporting/snapshots.py", "source_location": "L149", "weight": 1.0}, {"source": "snapshots_performancesnapshotfactory", "target": "snapshots_performancesnapshotfactory_build_metrics", "relation": "method", "confidence": "EXTRACTED", "source_file": "backtesting/reporting/snapshots.py", "source_location": "L171", "weight": 1.0}, {"source": "snapshots_performancesnapshotfactory", "target": "snapshots_performancesnapshotfactory_build_rolling_metrics", "relation": "method", "confidence": "EXTRACTED", "source_file": "backtesting/reporting/snapshots.py", "source_location": "L261", "weight": 1.0}, {"source": "snapshots_performancesnapshotfactory", "target": "snapshots_performancesnapshotfactory_build_drawdowns", "relation": "method", "confidence": "EXTRACTED", "source_file": "backtesting/reporting/snapshots.py", "source_location": "L306", "weight": 1.0}, {"source": "snapshots_performancesnapshotfactory", "target": "snapshots_performancesnapshotfactory_build_exposure", "relation": "method", "confidence": "EXTRACTED", "source_file": "backtesting/reporting/snapshots.py", "source_location": "L358", "weight": 1.0}, {"source": "snapshots_performancesnapshotfactory", "target": "snapshots_performancesnapshotfactory_build_sectors", "relation": "method", "confidence": "EXTRACTED", "source_file": "backtesting/reporting/snapshots.py", "source_location": "L373", "weight": 1.0}, {"source": "snapshots_performancesnapshotfactory", "target": "snapshots_performancesnapshotfactory_build_research", "relation": "method", "confidence": "EXTRACTED", "source_file": "backtesting/reporting/snapshots.py", "source_location": "L380", "weight": 1.0}, {"source": "snapshots_performancesnapshotfactory", "target": "snapshots_performancesnapshotfactory_latest_holdings_relative_performance", "relation": "method", "confidence": "EXTRACTED", "source_file": "backtesting/reporting/snapshots.py", "source_location": "L407", "weight": 1.0}, {"source": "snapshots_performancesnapshotfactory", "target": "snapshots_performancesnapshotfactory_compute_latest_holdings_returns", "relation": "method", "confidence": "EXTRACTED", "source_file": "backtesting/reporting/snapshots.py", "source_location": "L422", "weight": 1.0}, {"source": "backtesting_reporting_snapshots_py", "target": "snapshots_merge_latest_holdings_returns", "relation": "contains", "confidence": "EXTRACTED", "source_file": "backtesting/reporting/snapshots.py", "source_location": "L452", "weight": 1.0}, {"source": "backtesting_reporting_snapshots_py", "target": "snapshots_rank_latest_holdings", "relation": "contains", "confidence": "EXTRACTED", "source_file": "backtesting/reporting/snapshots.py", "source_location": "L475", "weight": 1.0}, {"source": "snapshots_performancesnapshotfactory", "target": "snapshots_performancesnapshotfactory_decorate_holding_symbols", "relation": "method", "confidence": "EXTRACTED", "source_file": "backtesting/reporting/snapshots.py", "source_location": "L484", "weight": 1.0}, {"source": "backtesting_reporting_snapshots_py", "target": "snapshots_latest_rebalance_date", "relation": "contains", "confidence": "EXTRACTED", "source_file": "backtesting/reporting/snapshots.py", "source_location": "L492", "weight": 1.0}, {"source": "backtesting_reporting_snapshots_py", "target": "snapshots_latest_holdings", "relation": "contains", "confidence": "EXTRACTED", "source_file": "backtesting/reporting/snapshots.py", "source_location": "L510", "weight": 1.0}, {"source": "backtesting_reporting_snapshots_py", "target": "snapshots_equity_from_returns", "relation": "contains", "confidence": "EXTRACTED", "source_file": "backtesting/reporting/snapshots.py", "source_location": "L523", "weight": 1.0}, {"source": "backtesting_reporting_snapshots_py", "target": "snapshots_cagr", "relation": "contains", "confidence": "EXTRACTED", "source_file": "backtesting/reporting/snapshots.py", "source_location": "L527", "weight": 1.0}, {"source": "backtesting_reporting_snapshots_py", "target": "snapshots_build_drawdown_record", "relation": "contains", "confidence": "EXTRACTED", "source_file": "backtesting/reporting/snapshots.py", "source_location": "L542", "weight": 1.0}, {"source": "snapshots_performancesnapshotfactory_build", "target": "snapshots_performancesnapshotfactory_load_benchmark", "relation": "calls", "confidence": "EXTRACTED", "source_file": "backtesting/reporting/snapshots.py", "source_location": "L84", "weight": 1.0}, {"source": "snapshots_performancesnapshotfactory_build", "target": "snapshots_performancesnapshotfactory_resolve_profile", "relation": "calls", "confidence": "EXTRACTED", "source_file": "backtesting/reporting/snapshots.py", "source_location": "L86", "weight": 1.0}, {"source": "snapshots_performancesnapshotfactory_build", "target": "snapshots_performancesnapshotfactory_build_rolling_metrics", "relation": "calls", "confidence": "EXTRACTED", "source_file": "backtesting/reporting/snapshots.py", "source_location": "L90", "weight": 1.0}, {"source": "snapshots_performancesnapshotfactory_build", "target": "snapshots_performancesnapshotfactory_build_drawdowns", "relation": "calls", "confidence": "EXTRACTED", "source_file": "backtesting/reporting/snapshots.py", "source_location": "L91", "weight": 1.0}, {"source": "snapshots_performancesnapshotfactory_build", "target": "snapshots_performancesnapshotfactory_build_exposure", "relation": "calls", "confidence": "EXTRACTED", "source_file": "backtesting/reporting/snapshots.py", "source_location": "L92", "weight": 1.0}, {"source": "snapshots_performancesnapshotfactory_build", "target": "snapshots_performancesnapshotfactory_build_sectors", "relation": "calls", "confidence": "EXTRACTED", "source_file": "backtesting/reporting/snapshots.py", "source_location": "L93", "weight": 1.0}, {"source": "snapshots_performancesnapshotfactory_build", "target": "snapshots_performancesnapshotfactory_build_research", "relation": "calls", "confidence": "EXTRACTED", "source_file": "backtesting/reporting/snapshots.py", "source_location": "L94", "weight": 1.0}, {"source": "snapshots_performancesnapshotfactory_build", "target": "snapshots_performancesnapshotfactory_build_metrics", "relation": "calls", "confidence": "EXTRACTED", "source_file": "backtesting/reporting/snapshots.py", "source_location": "L95", "weight": 1.0}, {"source": "snapshots_performancesnapshotfactory_build", "target": "snapshots_performancesnapshot", "relation": "calls", "confidence": "EXTRACTED", "source_file": "backtesting/reporting/snapshots.py", "source_location": "L105", "weight": 1.0}, {"source": "snapshots_performancesnapshotfactory_load_benchmark", "target": "snapshots_empty_series", "relation": "calls", "confidence": "EXTRACTED", "source_file": "backtesting/reporting/snapshots.py", "source_location": "L131", "weight": 1.0}, {"source": "snapshots_performancesnapshotfactory_load_benchmark", "target": "snapshots_equity_from_returns", "relation": "calls", "confidence": "EXTRACTED", "source_file": "backtesting/reporting/snapshots.py", "source_location": "L143", "weight": 1.0}, {"source": "snapshots_performancesnapshotfactory_build_metrics", "target": "snapshots_cagr", "relation": "calls", "confidence": "EXTRACTED", "source_file": "backtesting/reporting/snapshots.py", "source_location": "L186", "weight": 1.0}, {"source": "snapshots_performancesnapshotfactory_build_drawdowns", "target": "snapshots_build_drawdown_record", "relation": "calls", "confidence": "EXTRACTED", "source_file": "backtesting/reporting/snapshots.py", "source_location": "L327", "weight": 1.0}, {"source": "snapshots_performancesnapshotfactory_build_exposure", "target": "snapshots_latest_holdings", "relation": "calls", "confidence": "EXTRACTED", "source_file": "backtesting/reporting/snapshots.py", "source_location": "L360", "weight": 1.0}, {"source": "snapshots_performancesnapshotfactory_build_exposure", "target": "snapshots_performancesnapshotfactory_latest_holdings_relative_performance", "relation": "calls", "confidence": "EXTRACTED", "source_file": "backtesting/reporting/snapshots.py", "source_location": "L361", "weight": 1.0}, {"source": "snapshots_performancesnapshotfactory_build_exposure", "target": "snapshots_performancesnapshotfactory_decorate_holding_symbols", "relation": "calls", "confidence": "EXTRACTED", "source_file": "backtesting/reporting/snapshots.py", "source_location": "L362", "weight": 1.0}, {"source": "snapshots_performancesnapshotfactory_build_exposure", "target": "snapshots_rank_latest_holdings", "relation": "calls", "confidence": "EXTRACTED", "source_file": "backtesting/reporting/snapshots.py", "source_location": "L363", "weight": 1.0}, {"source": "snapshots_performancesnapshotfactory_latest_holdings_relative_performance", "target": "snapshots_merge_latest_holdings_returns", "relation": "calls", "confidence": "EXTRACTED", "source_file": "backtesting/reporting/snapshots.py", "source_location": "L415", "weight": 1.0}, {"source": "snapshots_performancesnapshotfactory_latest_holdings_relative_performance", "target": "snapshots_performancesnapshotfactory_compute_latest_holdings_returns", "relation": "calls", "confidence": "EXTRACTED", "source_file": "backtesting/reporting/snapshots.py", "source_location": "L417", "weight": 1.0}, {"source": "snapshots_performancesnapshotfactory_compute_latest_holdings_returns", "target": "snapshots_latest_rebalance_date", "relation": "calls", "confidence": "EXTRACTED", "source_file": "backtesting/reporting/snapshots.py", "source_location": "L429", "weight": 1.0}], "raw_calls": [{"caller_nid": "snapshots_default_benchmark", "callee": "default_kospi200", "source_file": "backtesting/reporting/snapshots.py", "source_location": "L44"}, {"caller_nid": "snapshots_empty_series", "callee": "Series", "source_file": "backtesting/reporting/snapshots.py", "source_location": "L48"}, {"caller_nid": "snapshots_performancesnapshotfactory_build", "callee": "sort_index", "source_file": "backtesting/reporting/snapshots.py", "source_location": "L82"}, {"caller_nid": "snapshots_performancesnapshotfactory_build", "callee": "astype", "source_file": "backtesting/reporting/snapshots.py", "source_location": "L82"}, {"caller_nid": "snapshots_performancesnapshotfactory_build", "callee": "sort_index", "source_file": "backtesting/reporting/snapshots.py", "source_location": "L83"}, {"caller_nid": "snapshots_performancesnapshotfactory_build", "callee": "astype", "source_file": "backtesting/reporting/snapshots.py", "source_location": "L83"}, {"caller_nid": "snapshots_performancesnapshotfactory_build", "callee": "str", "source_file": "backtesting/reporting/snapshots.py", "source_location": "L107"}, {"caller_nid": "snapshots_performancesnapshotfactory_build", "callee": "get", "source_file": "backtesting/reporting/snapshots.py", "source_location": "L107"}, {"caller_nid": "snapshots_performancesnapshotfactory_build", "callee": "str", "source_file": "backtesting/reporting/snapshots.py", "source_location": "L108"}, {"caller_nid": "snapshots_performancesnapshotfactory_build", "callee": "get", "source_file": "backtesting/reporting/snapshots.py", "source_location": "L108"}, {"caller_nid": "snapshots_performancesnapshotfactory_load_benchmark", "callee": "load_series", "source_file": "backtesting/reporting/snapshots.py", "source_location": "L134"}, {"caller_nid": "snapshots_performancesnapshotfactory_load_benchmark", "callee": "str", "source_file": "backtesting/reporting/snapshots.py", "source_location": "L136"}, {"caller_nid": "snapshots_performancesnapshotfactory_load_benchmark", "callee": "date", "source_file": "backtesting/reporting/snapshots.py", "source_location": "L136"}, {"caller_nid": "snapshots_performancesnapshotfactory_load_benchmark", "callee": "min", "source_file": "backtesting/reporting/snapshots.py", "source_location": "L136"}, {"caller_nid": "snapshots_performancesnapshotfactory_load_benchmark", "callee": "str", "source_file": "backtesting/reporting/snapshots.py", "source_location": "L137"}, {"caller_nid": "snapshots_performancesnapshotfactory_load_benchmark", "callee": "date", "source_file": "backtesting/reporting/snapshots.py", "source_location": "L137"}, {"caller_nid": "snapshots_performancesnapshotfactory_load_benchmark", "callee": "max", "source_file": "backtesting/reporting/snapshots.py", "source_location": "L137"}, {"caller_nid": "snapshots_performancesnapshotfactory_load_benchmark", "callee": "astype", "source_file": "backtesting/reporting/snapshots.py", "source_location": "L142"}, {"caller_nid": "snapshots_performancesnapshotfactory_load_benchmark", "callee": "fillna", "source_file": "backtesting/reporting/snapshots.py", "source_location": "L142"}, {"caller_nid": "snapshots_performancesnapshotfactory_load_benchmark", "callee": "reindex", "source_file": "backtesting/reporting/snapshots.py", "source_location": "L142"}, {"caller_nid": "snapshots_performancesnapshotfactory_load_benchmark", "callee": "float", "source_file": "backtesting/reporting/snapshots.py", "source_location": "L145"}, {"caller_nid": "snapshots_performancesnapshotfactory_load_benchmark", "callee": "rename", "source_file": "backtesting/reporting/snapshots.py", "source_location": "L147"}, {"caller_nid": "snapshots_performancesnapshotfactory_load_benchmark", "callee": "rename", "source_file": "backtesting/reporting/snapshots.py", "source_location": "L147"}, {"caller_nid": "snapshots_performancesnapshotfactory_resolve_profile", "callee": "normalize", "source_file": "backtesting/reporting/snapshots.py", "source_location": "L155"}, {"caller_nid": "snapshots_performancesnapshotfactory_resolve_profile", "callee": "normalize", "source_file": "backtesting/reporting/snapshots.py", "source_location": "L157"}, {"caller_nid": "snapshots_performancesnapshotfactory_resolve_profile", "callee": "get", "source_file": "backtesting/reporting/snapshots.py", "source_location": "L158"}, {"caller_nid": "snapshots_performancesnapshotfactory_resolve_profile", "callee": "get", "source_file": "backtesting/reporting/snapshots.py", "source_location": "L158"}, {"caller_nid": "snapshots_performancesnapshotfactory_resolve_profile", "callee": "lower", "source_file": "backtesting/reporting/snapshots.py", "source_location": "L164"}, {"caller_nid": "snapshots_performancesnapshotfactory_resolve_profile", "callee": "join", "source_file": "backtesting/reporting/snapshots.py", "source_location": "L164"}, {"caller_nid": "snapshots_performancesnapshotfactory_resolve_profile", "callee": "str", "source_file": "backtesting/reporting/snapshots.py", "source_location": "L165"}, {"caller_nid": "snapshots_performancesnapshotfactory_resolve_profile", "callee": "get", "source_file": "backtesting/reporting/snapshots.py", "source_location": "L165"}, {"caller_nid": "snapshots_performancesnapshotfactory_resolve_profile", "callee": "any", "source_file": "backtesting/reporting/snapshots.py", "source_location": "L167"}, {"caller_nid": "snapshots_performancesnapshotfactory_build_metrics", "callee": "monthly_return_series", "source_file": "backtesting/reporting/snapshots.py", "source_location": "L181"}, {"caller_nid": "snapshots_performancesnapshotfactory_build_metrics", "callee": "yearly_return_series", "source_file": "backtesting/reporting/snapshots.py", "source_location": "L182"}, {"caller_nid": "snapshots_performancesnapshotfactory_build_metrics", "callee": "annualized_volatility", "source_file": "backtesting/reporting/snapshots.py", "source_location": "L183"}, {"caller_nid": "snapshots_performancesnapshotfactory_build_metrics", "callee": "annualized_downside_deviation", "source_file": "backtesting/reporting/snapshots.py", "source_location": "L184"}, {"caller_nid": "snapshots_performancesnapshotfactory_build_metrics", "callee": "float", "source_file": "backtesting/reporting/snapshots.py", "source_location": "L185"}, {"caller_nid": "snapshots_performancesnapshotfactory_build_metrics", "callee": "float", "source_file": "backtesting/reporting/snapshots.py", "source_location": "L187"}, {"caller_nid": "snapshots_performancesnapshotfactory_build_metrics", "callee": "min", "source_file": "backtesting/reporting/snapshots.py", "source_location": "L187"}, {"caller_nid": "snapshots_performancesnapshotfactory_build_metrics", "callee": "abs", "source_file": "backtesting/reporting/snapshots.py", "source_location": "L188"}, {"caller_nid": "snapshots_performancesnapshotfactory_build_metrics", "callee": "float", "source_file": "backtesting/reporting/snapshots.py", "source_location": "L188"}, {"caller_nid": "snapshots_performancesnapshotfactory_build_metrics", "callee": "mean", "source_file": "backtesting/reporting/snapshots.py", "source_location": "L188"}, {"caller_nid": "snapshots_performancesnapshotfactory_build_metrics", "callee": "float", "source_file": "backtesting/reporting/snapshots.py", "source_location": "L189"}, {"caller_nid": "snapshots_performancesnapshotfactory_build_metrics", "callee": "abs", "source_file": "backtesting/reporting/snapshots.py", "source_location": "L189"}, {"caller_nid": "snapshots_performancesnapshotfactory_build_metrics", "callee": "astype", "source_file": "backtesting/reporting/snapshots.py", "source_location": "L190"}, {"caller_nid": "snapshots_performancesnapshotfactory_build_metrics", "callee": "dropna", "source_file": "backtesting/reporting/snapshots.py", "source_location": "L190"}, {"caller_nid": "snapshots_performancesnapshotfactory_build_metrics", "callee": "sub", "source_file": "backtesting/reporting/snapshots.py", "source_location": "L203"}, {"caller_nid": "snapshots_performancesnapshotfactory_build_metrics", "callee": "float", "source_file": "backtesting/reporting/snapshots.py", "source_location": "L204"}, {"caller_nid": "snapshots_performancesnapshotfactory_build_metrics", "callee": "var", "source_file": "backtesting/reporting/snapshots.py", "source_location": "L204"}, {"caller_nid": "snapshots_performancesnapshotfactory_build_metrics", "callee": "float", "source_file": "backtesting/reporting/snapshots.py", "source_location": "L205"}, {"caller_nid": "snapshots_performancesnapshotfactory_build_metrics", "callee": "cov", "source_file": "backtesting/reporting/snapshots.py", "source_location": "L205"}, {"caller_nid": "snapshots_performancesnapshotfactory_build_metrics", "callee": "abs", "source_file": "backtesting/reporting/snapshots.py", "source_location": "L206"}, {"caller_nid": "snapshots_performancesnapshotfactory_build_metrics", "callee": "float", "source_file": "backtesting/reporting/snapshots.py", "source_location": "L207"}, {"caller_nid": "snapshots_performancesnapshotfactory_build_metrics", "callee": "mean", "source_file": "backtesting/reporting/snapshots.py", "source_location": "L207"}, {"caller_nid": "snapshots_performancesnapshotfactory_build_metrics", "callee": "float", "source_file": "backtesting/reporting/snapshots.py", "source_location": "L207"}, {"caller_nid": "snapshots_performancesnapshotfactory_build_metrics", "callee": "mean", "source_file": "backtesting/reporting/snapshots.py", "source_location": "L207"}, {"caller_nid": "snapshots_performancesnapshotfactory_build_metrics", "callee": "annualized_volatility", "source_file": "backtesting/reporting/snapshots.py", "source_location": "L208"}, {"caller_nid": "snapshots_performancesnapshotfactory_build_metrics", "callee": "abs", "source_file": "backtesting/reporting/snapshots.py", "source_location": "L211"}, {"caller_nid": "snapshots_performancesnapshotfactory_build_metrics", "callee": "float", "source_file": "backtesting/reporting/snapshots.py", "source_location": "L212"}, {"caller_nid": "snapshots_performancesnapshotfactory_build_metrics", "callee": "mean", "source_file": "backtesting/reporting/snapshots.py", "source_location": "L212"}, {"caller_nid": "snapshots_performancesnapshotfactory_build_metrics", "callee": "float", "source_file": "backtesting/reporting/snapshots.py", "source_location": "L214"}, {"caller_nid": "snapshots_performancesnapshotfactory_build_metrics", "callee": "corr", "source_file": "backtesting/reporting/snapshots.py", "source_location": "L214"}, {"caller_nid": "snapshots_performancesnapshotfactory_build_metrics", "callee": "len", "source_file": "backtesting/reporting/snapshots.py", "source_location": "L214"}, {"caller_nid": "snapshots_performancesnapshotfactory_build_metrics", "callee": "isna", "source_file": "backtesting/reporting/snapshots.py", "source_location": "L215"}, {"caller_nid": "snapshots_performancesnapshotfactory_build_metrics", "callee": "capture_ratio", "source_file": "backtesting/reporting/snapshots.py", "source_location": "L216"}, {"caller_nid": "snapshots_performancesnapshotfactory_build_metrics", "callee": "capture_ratio", "source_file": "backtesting/reporting/snapshots.py", "source_location": "L217"}, {"caller_nid": "snapshots_performancesnapshotfactory_build_metrics", "callee": "float", "source_file": "backtesting/reporting/snapshots.py", "source_location": "L218"}, {"caller_nid": "snapshots_performancesnapshotfactory_build_metrics", "callee": "mean", "source_file": "backtesting/reporting/snapshots.py", "source_location": "L218"}, {"caller_nid": "snapshots_performancesnapshotfactory_build_metrics", "callee": "PerformanceMetrics", "source_file": "backtesting/reporting/snapshots.py", "source_location": "L221"}, {"caller_nid": "snapshots_performancesnapshotfactory_build_metrics", "callee": "annualized_sharpe", "source_file": "backtesting/reporting/snapshots.py", "source_location": "L225"}, {"caller_nid": "snapshots_performancesnapshotfactory_build_metrics", "callee": "float", "source_file": "backtesting/reporting/snapshots.py", "source_location": "L229"}, {"caller_nid": "snapshots_performancesnapshotfactory_build_metrics", "callee": "float", "source_file": "backtesting/reporting/snapshots.py", "source_location": "L230"}, {"caller_nid": "snapshots_performancesnapshotfactory_build_metrics", "callee": "mean", "source_file": "backtesting/reporting/snapshots.py", "source_location": "L230"}, {"caller_nid": "snapshots_performancesnapshotfactory_build_metrics", "callee": "fillna", "source_file": "backtesting/reporting/snapshots.py", "source_location": "L230"}, {"caller_nid": "snapshots_performancesnapshotfactory_build_metrics", "callee": "value_at_risk", "source_file": "backtesting/reporting/snapshots.py", "source_location": "L236"}, {"caller_nid": "snapshots_performancesnapshotfactory_build_metrics", "callee": "conditional_value_at_risk", "source_file": "backtesting/reporting/snapshots.py", "source_location": "L237"}, {"caller_nid": "snapshots_performancesnapshotfactory_build_metrics", "callee": "win_rate", "source_file": "backtesting/reporting/snapshots.py", "source_location": "L238"}, {"caller_nid": "snapshots_performancesnapshotfactory_build_metrics", "callee": "payoff_ratio", "source_file": "backtesting/reporting/snapshots.py", "source_location": "L239"}, {"caller_nid": "snapshots_performancesnapshotfactory_build_metrics", "callee": "profit_factor", "source_file": "backtesting/reporting/snapshots.py", "source_location": "L240"}, {"caller_nid": "snapshots_performancesnapshotfactory_build_metrics", "callee": "skewness", "source_file": "backtesting/reporting/snapshots.py", "source_location": "L241"}, {"caller_nid": "snapshots_performancesnapshotfactory_build_metrics", "callee": "kurtosis", "source_file": "backtesting/reporting/snapshots.py", "source_location": "L242"}, {"caller_nid": "snapshots_performancesnapshotfactory_build_metrics", "callee": "float", "source_file": "backtesting/reporting/snapshots.py", "source_location": "L243"}, {"caller_nid": "snapshots_performancesnapshotfactory_build_metrics", "callee": "max", "source_file": "backtesting/reporting/snapshots.py", "source_location": "L243"}, {"caller_nid": "snapshots_performancesnapshotfactory_build_metrics", "callee": "float", "source_file": "backtesting/reporting/snapshots.py", "source_location": "L244"}, {"caller_nid": "snapshots_performancesnapshotfactory_build_metrics", "callee": "min", "source_file": "backtesting/reporting/snapshots.py", "source_location": "L244"}, {"caller_nid": "snapshots_performancesnapshotfactory_build_metrics", "callee": "float", "source_file": "backtesting/reporting/snapshots.py", "source_location": "L245"}, {"caller_nid": "snapshots_performancesnapshotfactory_build_metrics", "callee": "max", "source_file": "backtesting/reporting/snapshots.py", "source_location": "L245"}, {"caller_nid": "snapshots_performancesnapshotfactory_build_metrics", "callee": "float", "source_file": "backtesting/reporting/snapshots.py", "source_location": "L246"}, {"caller_nid": "snapshots_performancesnapshotfactory_build_metrics", "callee": "min", "source_file": "backtesting/reporting/snapshots.py", "source_location": "L246"}, {"caller_nid": "snapshots_performancesnapshotfactory_build_metrics", "callee": "float", "source_file": "backtesting/reporting/snapshots.py", "source_location": "L247"}, {"caller_nid": "snapshots_performancesnapshotfactory_build_metrics", "callee": "max", "source_file": "backtesting/reporting/snapshots.py", "source_location": "L247"}, {"caller_nid": "snapshots_performancesnapshotfactory_build_metrics", "callee": "float", "source_file": "backtesting/reporting/snapshots.py", "source_location": "L248"}, {"caller_nid": "snapshots_performancesnapshotfactory_build_metrics", "callee": "min", "source_file": "backtesting/reporting/snapshots.py", "source_location": "L248"}, {"caller_nid": "snapshots_performancesnapshotfactory_build_metrics", "callee": "max_duration", "source_file": "backtesting/reporting/snapshots.py", "source_location": "L249"}, {"caller_nid": "snapshots_performancesnapshotfactory_build_metrics", "callee": "max_duration", "source_file": "backtesting/reporting/snapshots.py", "source_location": "L250"}, {"caller_nid": "snapshots_performancesnapshotfactory_build_metrics", "callee": "float", "source_file": "backtesting/reporting/snapshots.py", "source_location": "L251"}, {"caller_nid": "snapshots_performancesnapshotfactory_build_metrics", "callee": "hit_ratio", "source_file": "backtesting/reporting/snapshots.py", "source_location": "L252"}, {"caller_nid": "snapshots_performancesnapshotfactory_build_metrics", "callee": "hit_ratio", "source_file": "backtesting/reporting/snapshots.py", "source_location": "L253"}, {"caller_nid": "snapshots_performancesnapshotfactory_build_rolling_metrics", "callee": "rename", "source_file": "backtesting/reporting/snapshots.py", "source_location": "L269"}, {"caller_nid": "snapshots_performancesnapshotfactory_build_rolling_metrics", "callee": "apply", "source_file": "backtesting/reporting/snapshots.py", "source_location": "L269"}, {"caller_nid": "snapshots_performancesnapshotfactory_build_rolling_metrics", "callee": "rolling", "source_file": "backtesting/reporting/snapshots.py", "source_location": "L269"}, {"caller_nid": "snapshots_performancesnapshotfactory_build_rolling_metrics", "callee": "annualized_sharpe", "source_file": "backtesting/reporting/snapshots.py", "source_location": "L270"}, {"caller_nid": "snapshots_performancesnapshotfactory_build_rolling_metrics", "callee": "Series", "source_file": "backtesting/reporting/snapshots.py", "source_location": "L270"}, {"caller_nid": "snapshots_performancesnapshotfactory_build_rolling_metrics", "callee": "rolling_volatility", "source_file": "backtesting/reporting/snapshots.py", "source_location": "L273"}, {"caller_nid": "snapshots_performancesnapshotfactory_build_rolling_metrics", "callee": "rolling_return", "source_file": "backtesting/reporting/snapshots.py", "source_location": "L274"}, {"caller_nid": "snapshots_performancesnapshotfactory_build_rolling_metrics", "callee": "rolling_downside_deviation", "source_file": "backtesting/reporting/snapshots.py", "source_location": "L275"}, {"caller_nid": "snapshots_performancesnapshotfactory_build_rolling_metrics", "callee": "var", "source_file": "backtesting/reporting/snapshots.py", "source_location": "L278"}, {"caller_nid": "snapshots_performancesnapshotfactory_build_rolling_metrics", "callee": "rolling", "source_file": "backtesting/reporting/snapshots.py", "source_location": "L278"}, {"caller_nid": "snapshots_performancesnapshotfactory_build_rolling_metrics", "callee": "div", "source_file": "backtesting/reporting/snapshots.py", "source_location": "L279"}, {"caller_nid": "snapshots_performancesnapshotfactory_build_rolling_metrics", "callee": "cov", "source_file": "backtesting/reporting/snapshots.py", "source_location": "L279"}, {"caller_nid": "snapshots_performancesnapshotfactory_build_rolling_metrics", "callee": "rolling", "source_file": "backtesting/reporting/snapshots.py", "source_location": "L279"}, {"caller_nid": "snapshots_performancesnapshotfactory_build_rolling_metrics", "callee": "replace", "source_file": "backtesting/reporting/snapshots.py", "source_location": "L282"}, {"caller_nid": "snapshots_performancesnapshotfactory_build_rolling_metrics", "callee": "float", "source_file": "backtesting/reporting/snapshots.py", "source_location": "L282"}, {"caller_nid": "snapshots_performancesnapshotfactory_build_rolling_metrics", "callee": "float", "source_file": "backtesting/reporting/snapshots.py", "source_location": "L282"}, {"caller_nid": "snapshots_performancesnapshotfactory_build_rolling_metrics", "callee": "corr", "source_file": "backtesting/reporting/snapshots.py", "source_location": "L283"}, {"caller_nid": "snapshots_performancesnapshotfactory_build_rolling_metrics", "callee": "rolling", "source_file": "backtesting/reporting/snapshots.py", "source_location": "L283"}, {"caller_nid": "snapshots_performancesnapshotfactory_build_rolling_metrics", "callee": "sub", "source_file": "backtesting/reporting/snapshots.py", "source_location": "L284"}, {"caller_nid": "snapshots_performancesnapshotfactory_build_rolling_metrics", "callee": "mul", "source_file": "backtesting/reporting/snapshots.py", "source_location": "L285"}, {"caller_nid": "snapshots_performancesnapshotfactory_build_rolling_metrics", "callee": "std", "source_file": "backtesting/reporting/snapshots.py", "source_location": "L285"}, {"caller_nid": "snapshots_performancesnapshotfactory_build_rolling_metrics", "callee": "rolling", "source_file": "backtesting/reporting/snapshots.py", "source_location": "L285"}, {"caller_nid": "snapshots_performancesnapshotfactory_build_rolling_metrics", "callee": "div", "source_file": "backtesting/reporting/snapshots.py", "source_location": "L288"}, {"caller_nid": "snapshots_performancesnapshotfactory_build_rolling_metrics", "callee": "mul", "source_file": "backtesting/reporting/snapshots.py", "source_location": "L288"}, {"caller_nid": "snapshots_performancesnapshotfactory_build_rolling_metrics", "callee": "mean", "source_file": "backtesting/reporting/snapshots.py", "source_location": "L288"}, {"caller_nid": "snapshots_performancesnapshotfactory_build_rolling_metrics", "callee": "rolling", "source_file": "backtesting/reporting/snapshots.py", "source_location": "L288"}, {"caller_nid": "snapshots_performancesnapshotfactory_build_rolling_metrics", "callee": "replace", "source_file": "backtesting/reporting/snapshots.py", "source_location": "L289"}, {"caller_nid": "snapshots_performancesnapshotfactory_build_rolling_metrics", "callee": "mul", "source_file": "backtesting/reporting/snapshots.py", "source_location": "L291"}, {"caller_nid": "snapshots_performancesnapshotfactory_build_rolling_metrics", "callee": "mean", "source_file": "backtesting/reporting/snapshots.py", "source_location": "L292"}, {"caller_nid": "snapshots_performancesnapshotfactory_build_rolling_metrics", "callee": "rolling", "source_file": "backtesting/reporting/snapshots.py", "source_location": "L292"}, {"caller_nid": "snapshots_performancesnapshotfactory_build_rolling_metrics", "callee": "mean", "source_file": "backtesting/reporting/snapshots.py", "source_location": "L293"}, {"caller_nid": "snapshots_performancesnapshotfactory_build_rolling_metrics", "callee": "rolling", "source_file": "backtesting/reporting/snapshots.py", "source_location": "L293"}, {"caller_nid": "snapshots_performancesnapshotfactory_build_rolling_metrics", "callee": "update", "source_file": "backtesting/reporting/snapshots.py", "source_location": "L295"}, {"caller_nid": "snapshots_performancesnapshotfactory_build_rolling_metrics", "callee": "rename", "source_file": "backtesting/reporting/snapshots.py", "source_location": "L297"}, {"caller_nid": "snapshots_performancesnapshotfactory_build_rolling_metrics", "callee": "rename", "source_file": "backtesting/reporting/snapshots.py", "source_location": "L298"}, {"caller_nid": "snapshots_performancesnapshotfactory_build_rolling_metrics", "callee": "rename", "source_file": "backtesting/reporting/snapshots.py", "source_location": "L299"}, {"caller_nid": "snapshots_performancesnapshotfactory_build_rolling_metrics", "callee": "rename", "source_file": "backtesting/reporting/snapshots.py", "source_location": "L300"}, {"caller_nid": "snapshots_performancesnapshotfactory_build_rolling_metrics", "callee": "rename", "source_file": "backtesting/reporting/snapshots.py", "source_location": "L301"}, {"caller_nid": "snapshots_performancesnapshotfactory_build_rolling_metrics", "callee": "RollingMetrics", "source_file": "backtesting/reporting/snapshots.py", "source_location": "L304"}, {"caller_nid": "snapshots_performancesnapshotfactory_build_drawdowns", "callee": "cummax", "source_file": "backtesting/reporting/snapshots.py", "source_location": "L307"}, {"caller_nid": "snapshots_performancesnapshotfactory_build_drawdowns", "callee": "rename", "source_file": "backtesting/reporting/snapshots.py", "source_location": "L308"}, {"caller_nid": "snapshots_performancesnapshotfactory_build_drawdowns", "callee": "sub", "source_file": "backtesting/reporting/snapshots.py", "source_location": "L308"}, {"caller_nid": "snapshots_performancesnapshotfactory_build_drawdowns", "callee": "div", "source_file": "backtesting/reporting/snapshots.py", "source_location": "L308"}, {"caller_nid": "snapshots_performancesnapshotfactory_build_drawdowns", "callee": "items", "source_file": "backtesting/reporting/snapshots.py", "source_location": "L314"}, {"caller_nid": "snapshots_performancesnapshotfactory_build_drawdowns", "callee": "float", "source_file": "backtesting/reporting/snapshots.py", "source_location": "L315"}, {"caller_nid": "snapshots_performancesnapshotfactory_build_drawdowns", "callee": "append", "source_file": "backtesting/reporting/snapshots.py", "source_location": "L327"}, {"caller_nid": "snapshots_performancesnapshotfactory_build_drawdowns", "callee": "append", "source_file": "backtesting/reporting/snapshots.py", "source_location": "L331"}, {"caller_nid": "snapshots_performancesnapshotfactory_build_drawdowns", "callee": "from_records", "source_file": "backtesting/reporting/snapshots.py", "source_location": "L342"}, {"caller_nid": "snapshots_performancesnapshotfactory_build_drawdowns", "callee": "DrawdownStats", "source_file": "backtesting/reporting/snapshots.py", "source_location": "L356"}, {"caller_nid": "snapshots_performancesnapshotfactory_build_exposure", "callee": "rename", "source_file": "backtesting/reporting/snapshots.py", "source_location": "L359"}, {"caller_nid": "snapshots_performancesnapshotfactory_build_exposure", "callee": "sum", "source_file": "backtesting/reporting/snapshots.py", "source_location": "L359"}, {"caller_nid": "snapshots_performancesnapshotfactory_build_exposure", "callee": "ne", "source_file": "backtesting/reporting/snapshots.py", "source_location": "L359"}, {"caller_nid": "snapshots_performancesnapshotfactory_build_exposure", "callee": "fillna", "source_file": "backtesting/reporting/snapshots.py", "source_location": "L359"}, {"caller_nid": "snapshots_performancesnapshotfactory_build_exposure", "callee": "copy", "source_file": "backtesting/reporting/snapshots.py", "source_location": "L360"}, {"caller_nid": "snapshots_performancesnapshotfactory_build_exposure", "callee": "ExposureSnapshot", "source_file": "backtesting/reporting/snapshots.py", "source_location": "L365"}, {"caller_nid": "snapshots_performancesnapshotfactory_build_exposure", "callee": "astype", "source_file": "backtesting/reporting/snapshots.py", "source_location": "L366"}, {"caller_nid": "snapshots_performancesnapshotfactory_build_exposure", "callee": "rename", "source_file": "backtesting/reporting/snapshots.py", "source_location": "L368"}, {"caller_nid": "snapshots_performancesnapshotfactory_build_exposure", "callee": "astype", "source_file": "backtesting/reporting/snapshots.py", "source_location": "L368"}, {"caller_nid": "snapshots_performancesnapshotfactory_build_exposure", "callee": "fillna", "source_file": "backtesting/reporting/snapshots.py", "source_location": "L368"}, {"caller_nid": "snapshots_performancesnapshotfactory_build_sectors", "callee": "latest_sector_weights", "source_file": "backtesting/reporting/snapshots.py", "source_location": "L374"}, {"caller_nid": "snapshots_performancesnapshotfactory_build_sectors", "callee": "ne", "source_file": "backtesting/reporting/snapshots.py", "source_location": "L375"}, {"caller_nid": "snapshots_performancesnapshotfactory_build_sectors", "callee": "latest_sector_counts", "source_file": "backtesting/reporting/snapshots.py", "source_location": "L376"}, {"caller_nid": "snapshots_performancesnapshotfactory_build_sectors", "callee": "rename", "source_file": "backtesting/reporting/snapshots.py", "source_location": "L377"}, {"caller_nid": "snapshots_performancesnapshotfactory_build_sectors", "callee": "sort_values", "source_file": "backtesting/reporting/snapshots.py", "source_location": "L377"}, {"caller_nid": "snapshots_performancesnapshotfactory_build_sectors", "callee": "abs", "source_file": "backtesting/reporting/snapshots.py", "source_location": "L377"}, {"caller_nid": "snapshots_performancesnapshotfactory_build_sectors", "callee": "SectorSnapshot", "source_file": "backtesting/reporting/snapshots.py", "source_location": "L378"}, {"caller_nid": "snapshots_performancesnapshotfactory_build_research", "callee": "sector_weight_timeseries", "source_file": "backtesting/reporting/snapshots.py", "source_location": "L388"}, {"caller_nid": "snapshots_performancesnapshotfactory_build_research", "callee": "sector_contribution_timeseries", "source_file": "backtesting/reporting/snapshots.py", "source_location": "L389"}, {"caller_nid": "snapshots_performancesnapshotfactory_build_research", "callee": "sort_values", "source_file": "backtesting/reporting/snapshots.py", "source_location": "L390"}, {"caller_nid": "snapshots_performancesnapshotfactory_build_research", "callee": "ResearchSnapshot", "source_file": "backtesting/reporting/snapshots.py", "source_location": "L391"}, {"caller_nid": "snapshots_performancesnapshotfactory_build_research", "callee": "build_monthly_heatmap", "source_file": "backtesting/reporting/snapshots.py", "source_location": "L392"}, {"caller_nid": "snapshots_performancesnapshotfactory_build_research", "callee": "build_return_distribution", "source_file": "backtesting/reporting/snapshots.py", "source_location": "L393"}, {"caller_nid": "snapshots_performancesnapshotfactory_build_research", "callee": "build_return_distribution", "source_file": "backtesting/reporting/snapshots.py", "source_location": "L394"}, {"caller_nid": "snapshots_performancesnapshotfactory_build_research", "callee": "monthly_return_series", "source_file": "backtesting/reporting/snapshots.py", "source_location": "L394"}, {"caller_nid": "snapshots_performancesnapshotfactory_build_research", "callee": "yearly_return_series", "source_file": "backtesting/reporting/snapshots.py", "source_location": "L395"}, {"caller_nid": "snapshots_performancesnapshotfactory_build_research", "callee": "build_yearly_excess_returns", "source_file": "backtesting/reporting/snapshots.py", "source_location": "L397"}, {"caller_nid": "snapshots_performancesnapshotfactory_build_research", "callee": "Series", "source_file": "backtesting/reporting/snapshots.py", "source_location": "L399"}, {"caller_nid": "snapshots_performancesnapshotfactory_latest_holdings_relative_performance", "callee": "DataFrame", "source_file": "backtesting/reporting/snapshots.py", "source_location": "L409"}, {"caller_nid": "snapshots_performancesnapshotfactory_latest_holdings_relative_performance", "callee": "exists", "source_file": "backtesting/reporting/snapshots.py", "source_location": "L413"}, {"caller_nid": "snapshots_performancesnapshotfactory_latest_holdings_relative_performance", "callee": "read_csv", "source_file": "backtesting/reporting/snapshots.py", "source_location": "L414"}, {"caller_nid": "snapshots_performancesnapshotfactory_latest_holdings_relative_performance", "callee": "DataFrame", "source_file": "backtesting/reporting/snapshots.py", "source_location": "L419"}, {"caller_nid": "snapshots_performancesnapshotfactory_compute_latest_holdings_returns", "callee": "DataFrame", "source_file": "backtesting/reporting/snapshots.py", "source_location": "L425"}, {"caller_nid": "snapshots_performancesnapshotfactory_compute_latest_holdings_returns", "callee": "str", "source_file": "backtesting/reporting/snapshots.py", "source_location": "L427"}, {"caller_nid": "snapshots_performancesnapshotfactory_compute_latest_holdings_returns", "callee": "Timestamp", "source_file": "backtesting/reporting/snapshots.py", "source_location": "L428"}, {"caller_nid": "snapshots_performancesnapshotfactory_compute_latest_holdings_returns", "callee": "max", "source_file": "backtesting/reporting/snapshots.py", "source_location": "L428"}, {"caller_nid": "snapshots_performancesnapshotfactory_compute_latest_holdings_returns", "callee": "DataFrame", "source_file": "backtesting/reporting/snapshots.py", "source_location": "L431"}, {"caller_nid": "snapshots_performancesnapshotfactory_compute_latest_holdings_returns", "callee": "sort_index", "source_file": "backtesting/reporting/snapshots.py", "source_location": "L433"}, {"caller_nid": "snapshots_performancesnapshotfactory_compute_latest_holdings_returns", "callee": "reindex", "source_file": "backtesting/reporting/snapshots.py", "source_location": "L433"}, {"caller_nid": "snapshots_performancesnapshotfactory_compute_latest_holdings_returns", "callee": "dropna", "source_file": "backtesting/reporting/snapshots.py", "source_location": "L436"}, {"caller_nid": "snapshots_performancesnapshotfactory_compute_latest_holdings_returns", "callee": "float", "source_file": "backtesting/reporting/snapshots.py", "source_location": "L439"}, {"caller_nid": "snapshots_performancesnapshotfactory_compute_latest_holdings_returns", "callee": "float", "source_file": "backtesting/reporting/snapshots.py", "source_location": "L440"}, {"caller_nid": "snapshots_performancesnapshotfactory_compute_latest_holdings_returns", "callee": "append", "source_file": "backtesting/reporting/snapshots.py", "source_location": "L443"}, {"caller_nid": "snapshots_performancesnapshotfactory_compute_latest_holdings_returns", "callee": "DataFrame", "source_file": "backtesting/reporting/snapshots.py", "source_location": "L449"}, {"caller_nid": "snapshots_merge_latest_holdings_returns", "callee": "DataFrame", "source_file": "backtesting/reporting/snapshots.py", "source_location": "L454"}, {"caller_nid": "snapshots_merge_latest_holdings_returns", "callee": "copy", "source_file": "backtesting/reporting/snapshots.py", "source_location": "L456"}, {"caller_nid": "snapshots_merge_latest_holdings_returns", "callee": "merge", "source_file": "backtesting/reporting/snapshots.py", "source_location": "L457"}, {"caller_nid": "snapshots_merge_latest_holdings_returns", "callee": "DataFrame", "source_file": "backtesting/reporting/snapshots.py", "source_location": "L463"}, {"caller_nid": "snapshots_merge_latest_holdings_returns", "callee": "to_numeric", "source_file": "backtesting/reporting/snapshots.py", "source_location": "L466"}, {"caller_nid": "snapshots_merge_latest_holdings_returns", "callee": "dropna", "source_file": "backtesting/reporting/snapshots.py", "source_location": "L467"}, {"caller_nid": "snapshots_merge_latest_holdings_returns", "callee": "replace", "source_file": "backtesting/reporting/snapshots.py", "source_location": "L467"}, {"caller_nid": "snapshots_merge_latest_holdings_returns", "callee": "float", "source_file": "backtesting/reporting/snapshots.py", "source_location": "L467"}, {"caller_nid": "snapshots_merge_latest_holdings_returns", "callee": "float", "source_file": "backtesting/reporting/snapshots.py", "source_location": "L467"}, {"caller_nid": "snapshots_merge_latest_holdings_returns", "callee": "reset_index", "source_file": "backtesting/reporting/snapshots.py", "source_location": "L470"}, {"caller_nid": "snapshots_rank_latest_holdings", "callee": "DataFrame", "source_file": "backtesting/reporting/snapshots.py", "source_location": "L477"}, {"caller_nid": "snapshots_rank_latest_holdings", "callee": "sort_values", "source_file": "backtesting/reporting/snapshots.py", "source_location": "L478"}, {"caller_nid": "snapshots_rank_latest_holdings", "callee": "reset_index", "source_file": "backtesting/reporting/snapshots.py", "source_location": "L482"}, {"caller_nid": "snapshots_rank_latest_holdings", "callee": "head", "source_file": "backtesting/reporting/snapshots.py", "source_location": "L482"}, {"caller_nid": "snapshots_performancesnapshotfactory_decorate_holding_symbols", "callee": "copy", "source_file": "backtesting/reporting/snapshots.py", "source_location": "L487"}, {"caller_nid": "snapshots_performancesnapshotfactory_decorate_holding_symbols", "callee": "map", "source_file": "backtesting/reporting/snapshots.py", "source_location": "L488"}, {"caller_nid": "snapshots_performancesnapshotfactory_decorate_holding_symbols", "callee": "display_symbol", "source_file": "backtesting/reporting/snapshots.py", "source_location": "L488"}, {"caller_nid": "snapshots_performancesnapshotfactory_decorate_holding_symbols", "callee": "str", "source_file": "backtesting/reporting/snapshots.py", "source_location": "L488"}, {"caller_nid": "snapshots_latest_rebalance_date", "callee": "sort_index", "source_file": "backtesting/reporting/snapshots.py", "source_location": "L496"}, {"caller_nid": "snapshots_latest_rebalance_date", "callee": "astype", "source_file": "backtesting/reporting/snapshots.py", "source_location": "L496"}, {"caller_nid": "snapshots_latest_rebalance_date", "callee": "fillna", "source_file": "backtesting/reporting/snapshots.py", "source_location": "L496"}, {"caller_nid": "snapshots_latest_rebalance_date", "callee": "all", "source_file": "backtesting/reporting/snapshots.py", "source_location": "L498"}, {"caller_nid": "snapshots_latest_rebalance_date", "callee": "eq", "source_file": "backtesting/reporting/snapshots.py", "source_location": "L498"}, {"caller_nid": "snapshots_latest_rebalance_date", "callee": "Timestamp", "source_file": "backtesting/reporting/snapshots.py", "source_location": "L501"}, {"caller_nid": "snapshots_latest_rebalance_date", "callee": "range", "source_file": "backtesting/reporting/snapshots.py", "source_location": "L502"}, {"caller_nid": "snapshots_latest_rebalance_date", "callee": "len", "source_file": "backtesting/reporting/snapshots.py", "source_location": "L502"}, {"caller_nid": "snapshots_latest_rebalance_date", "callee": "allclose", "source_file": "backtesting/reporting/snapshots.py", "source_location": "L504"}, {"caller_nid": "snapshots_latest_rebalance_date", "callee": "to_numpy", "source_file": "backtesting/reporting/snapshots.py", "source_location": "L504"}, {"caller_nid": "snapshots_latest_rebalance_date", "callee": "to_numpy", "source_file": "backtesting/reporting/snapshots.py", "source_location": "L504"}, {"caller_nid": "snapshots_latest_rebalance_date", "callee": "Timestamp", "source_file": "backtesting/reporting/snapshots.py", "source_location": "L506"}, {"caller_nid": "snapshots_latest_holdings", "callee": "astype", "source_file": "backtesting/reporting/snapshots.py", "source_location": "L511"}, {"caller_nid": "snapshots_latest_holdings", "callee": "DataFrame", "source_file": "backtesting/reporting/snapshots.py", "source_location": "L512"}, {"caller_nid": "snapshots_latest_holdings", "callee": "copy", "source_file": "backtesting/reporting/snapshots.py", "source_location": "L518"}, {"caller_nid": "snapshots_latest_holdings", "callee": "ne", "source_file": "backtesting/reporting/snapshots.py", "source_location": "L518"}, {"caller_nid": "snapshots_latest_holdings", "callee": "abs", "source_file": "backtesting/reporting/snapshots.py", "source_location": "L519"}, {"caller_nid": "snapshots_latest_holdings", "callee": "reset_index", "source_file": "backtesting/reporting/snapshots.py", "source_location": "L520"}, {"caller_nid": "snapshots_latest_holdings", "callee": "sort_values", "source_file": "backtesting/reporting/snapshots.py", "source_location": "L520"}, {"caller_nid": "snapshots_equity_from_returns", "callee": "rename", "source_file": "backtesting/reporting/snapshots.py", "source_location": "L524"}, {"caller_nid": "snapshots_equity_from_returns", "callee": "mul", "source_file": "backtesting/reporting/snapshots.py", "source_location": "L524"}, {"caller_nid": "snapshots_equity_from_returns", "callee": "cumprod", "source_file": "backtesting/reporting/snapshots.py", "source_location": "L524"}, {"caller_nid": "snapshots_equity_from_returns", "callee": "fillna", "source_file": "backtesting/reporting/snapshots.py", "source_location": "L524"}, {"caller_nid": "snapshots_cagr", "callee": "len", "source_file": "backtesting/reporting/snapshots.py", "source_location": "L528"}, {"caller_nid": "snapshots_cagr", "callee": "float", "source_file": "backtesting/reporting/snapshots.py", "source_location": "L531"}, {"caller_nid": "snapshots_cagr", "callee": "float", "source_file": "backtesting/reporting/snapshots.py", "source_location": "L532"}, {"caller_nid": "snapshots_cagr", "callee": "len", "source_file": "backtesting/reporting/snapshots.py", "source_location": "L536"}, {"caller_nid": "snapshots_cagr", "callee": "float", "source_file": "backtesting/reporting/snapshots.py", "source_location": "L536"}, {"caller_nid": "snapshots_cagr", "callee": "float", "source_file": "backtesting/reporting/snapshots.py", "source_location": "L539"}, {"caller_nid": "snapshots_build_drawdown_record", "callee": "Timestamp", "source_file": "backtesting/reporting/snapshots.py", "source_location": "L551"}, {"caller_nid": "snapshots_build_drawdown_record", "callee": "Timestamp", "source_file": "backtesting/reporting/snapshots.py", "source_location": "L552"}, {"caller_nid": "snapshots_build_drawdown_record", "callee": "Timestamp", "source_file": "backtesting/reporting/snapshots.py", "source_location": "L553"}, {"caller_nid": "snapshots_build_drawdown_record", "callee": "Timestamp", "source_file": "backtesting/reporting/snapshots.py", "source_location": "L554"}, {"caller_nid": "snapshots_build_drawdown_record", "callee": "float", "source_file": "backtesting/reporting/snapshots.py", "source_location": "L560"}, {"caller_nid": "snapshots_build_drawdown_record", "callee": "int", "source_file": "backtesting/reporting/snapshots.py", "source_location": "L561"}, {"caller_nid": "snapshots_build_drawdown_record", "callee": "int", "source_file": "backtesting/reporting/snapshots.py", "source_location": "L562"}, {"caller_nid": "snapshots_build_drawdown_record", "callee": "int", "source_file": "backtesting/reporting/snapshots.py", "source_location": "L563"}]}